stache_tools/__init__.py
stache_tools/py.typed
stache_tools/cli/__init__.py
stache_tools/cli/__main__.py
stache_tools/cli/documents.py
stache_tools/cli/health.py
stache_tools/cli/ingest.py
stache_tools/cli/main.py
stache_tools/cli/models.py
stache_tools/cli/namespaces.py
stache_tools/cli/search.py
stache_tools/client/__init__.py
stache_tools/client/api.py
stache_tools/client/config.py
stache_tools/client/exceptions.py
stache_tools/client/factory.py
stache_tools/client/http.py
stache_tools/client/lambda_transport.py
stache_tools/client/retry.py
stache_tools/client/transport.py
stache_tools/loaders/__init__.py
stache_tools/loaders/base.py
stache_tools/loaders/pdf.py
stache_tools/loaders/registry.py
stache_tools/loaders/text.py
stache_tools/mcp/__init__.py
stache_tools/mcp/__main__.py
stache_tools/mcp/formatters.py
stache_tools/mcp/server.py
stache_tools/mcp/tools.py
stache_tools/plugins/__init__.py
stache_tools/plugins/base.py
stache_tools/plugins/enrichment.py
stache_tools/plugins/ocr.py
stache_tools-0.1.0.dist-info/METADATA
stache_tools-0.1.0.dist-info/WHEEL
stache_tools-0.1.0.dist-info/entry_points.txt
stache_tools-0.1.0.dist-info/licenses/LICENSE
stache_tools-0.1.0.dist-info/RECORD
