Metadata-Version: 2.4
Name: stache-tools
Version: 0.1.0
Summary: Utilities and tools for the Stache RAG system
Project-URL: Homepage, https://github.com/stache-ai/stache-tools
Project-URL: Repository, https://github.com/stache-ai/stache-tools
Project-URL: Issues, https://github.com/stache-ai/stache-tools/issues
Author: Stache Team
License: MIT
License-File: LICENSE
Keywords: cli,mcp,rag,stache
Classifier: Development Status :: 3 - Alpha
Classifier: Environment :: Console
Classifier: Intended Audience :: Developers
Classifier: License :: OSI Approved :: MIT License
Classifier: Programming Language :: Python :: 3
Classifier: Programming Language :: Python :: 3.10
Classifier: Programming Language :: Python :: 3.11
Classifier: Programming Language :: Python :: 3.12
Classifier: Topic :: Software Development :: Libraries :: Python Modules
Requires-Python: >=3.10
Requires-Dist: click>=8.0
Requires-Dist: httpx-auth>=0.22.0
Requires-Dist: httpx>=0.27.0
Requires-Dist: mcp<2.0.0,>=1.0.0
Requires-Dist: pydantic-settings>=2.0
Requires-Dist: pydantic>=2.0
Requires-Dist: pypdf>=4.0.0
Requires-Dist: python-dotenv>=1.0.0
Requires-Dist: rich>=13.0
Requires-Dist: tenacity>=8.0.0
Provides-Extra: all
Requires-Dist: boto3>=1.26.0; extra == 'all'
Provides-Extra: dev
Requires-Dist: boto3>=1.26.0; extra == 'dev'
Requires-Dist: moto>=5.0.0; extra == 'dev'
Requires-Dist: pytest-asyncio>=0.23.0; extra == 'dev'
Requires-Dist: pytest-cov>=4.0.0; extra == 'dev'
Requires-Dist: pytest>=8.0.0; extra == 'dev'
Requires-Dist: respx>=0.21.0; extra == 'dev'
Requires-Dist: ruff>=0.4.0; extra == 'dev'
Provides-Extra: lambda
Requires-Dist: boto3>=1.26.0; extra == 'lambda'
